LICENSE
MANIFEST.in
README.rst
setup.py
django_tiamat.egg-info/PKG-INFO
django_tiamat.egg-info/SOURCES.txt
django_tiamat.egg-info/dependency_links.txt
django_tiamat.egg-info/requires.txt
django_tiamat.egg-info/top_level.txt
tiamat/__init__.py
tiamat/decorators.py
tiamat/mail.py
tiamat/models.py
tiamat/paginate.py
tiamat/urlencoder.py
tiamat/templates/tiamat/_form.html
tiamat/templatetags/__init__.py
tiamat/templatetags/tiamat_tags.py
tiamat/tests/__init__.py
tiamat/tests/forms.py
tiamat/tests/models.py
tiamat/tests/run_tests.py
tiamat/tests/test_settings.py
tiamat/tests/tests.py