Metadata-Version: 1.1
Name: django-tiamat
Version: 0.9.8
Summary: 
